MANIFEST.in
NEWS.txt
README.rst
setup.py
bin/mom_namelist
data/input.ref
mom_utils/__init__.py
mom_utils/drifters.py
mom_utils/mom4.py
mom_utils/mom4_namelist.py
mom_utils/mom_output.py
mom_utils/utils.py
mom_utils.egg-info/PKG-INFO
mom_utils.egg-info/SOURCES.txt
mom_utils.egg-info/dependency_links.txt
mom_utils.egg-info/requires.txt
mom_utils.egg-info/top_level.txt
mom_utils.egg-info/zip-safe