Metadata-Version: 1.1
Name: mom-utils
Version: 1.2.6
Summary: Python utilities for the GFDL's numerical model MOM
Home-page: https://github.com/castelao/mom-utils
Author: Guilherme Castelao, Luiz Irber
Author-email: guilherme@castelao.net, luiz.irber@gmail.com
License: PSF
Platform: any
Classifier: Development Status :: 4 - Beta
Classifier: Intended Audience :: Developers
Classifier: Intended Audience :: Science/Research
Classifier: License :: OSI Approved :: Python Software Foundation License
Classifier: Operating System :: OS Independent
Classifier: Programming Language :: Python
Classifier: Programming Language :: Python :: 2
Classifier: Topic :: Scientific/Engineering
Classifier: Topic :: Software Development :: Libraries :: Python Modules
